BinaryCounters.py
BinaryCounters-0.0.3.dist-info/LICENSE
BinaryCounters-0.0.3.dist-info/METADATA
BinaryCounters-0.0.3.dist-info/WHEEL
BinaryCounters-0.0.3.dist-info/top_level.txt
BinaryCounters-0.0.3.dist-info/RECORD
