Metadata-Version: 2.1
Name: BinaryCounters
Version: 0.0.3
Summary: array based binary counters with useful functions attached
Home-page: https://github.com/altruios/BinaryCounters
Author: paul kosmala
Author-email: paul.kosmala@gmail.com
License: UNKNOWN
Platform: UNKNOWN
Classifier: Development Status :: 1 - Planning
Classifier: Programming Language :: Python :: 2
Classifier: Programming Language :: Python :: 2.7
Classifier: Programming Language :: Python :: 3
Classifier: Programming Language :: Python :: 3.4
Classifier: Programming Language :: Python :: 3.5
Classifier: License :: OSI Approved :: MIT License
Classifier: Operating System :: OS Independent
License-File: LICENSE
